ocgis/__init__.py
ocgis/attribute_maps.py
ocgis/ocgisapp.py
ocgis-cfu/__init__.py
ocgis-cfu/attribute_maps.py
ocgis-cfu/ocgisapp.py
ocgis_cfu-1.0.0.dist-info/METADATA
ocgis_cfu-1.0.0.dist-info/WHEEL
ocgis_cfu-1.0.0.dist-info/top_level.txt
ocgis_cfu-1.0.0.dist-info/RECORD
