Metadata-Version: 2.1
Name: ocgis-cfu
Version: 1.0.0
Summary: Import Iowa one call tickets into ArcGIS Online maps.
Author-email: Luke Shuttleworth <luke.shuttleworth@cfunet.net>
License: MIT
Project-URL: Source, https://github.com/luke-shuttleworth-cfu/OneMapIowa
Requires-Dist: arcgis>=2.1.0
Requires-Dist: beautifulsoup4>=4.12.2
Requires-Dist: lxml>=4.9.3
Requires-Dist: selenium>=4.22.0
